{"_ts":[1496306988],"_r":{"breakdown":{"html":{"bytes":[7799],"requests":[4]},"js":{"bytes":[107203],"requests":[8]},"css":{"bytes":[25470],"requests":[4]},"image":{"bytes":[2047607],"requests":[15]},"flash":{"bytes":[0],"requests":[0]},"font":{"bytes":[225349],"requests":[2]},"other":{"bytes":[0],"requests":[0]}},"date":[1496306988],"domElements":[291],"domInteractive":[1318],"firstPaint":[1493],"fullyLoaded":[4883],"id":["170601_ED_HCA"],"loadTime":[4816],"render":[2790],"SpeedIndex":[3048],"TTFB":[216],"videoFrames":[[{"_i":"frame_0000.jpg","_t":0,"_vc":0},{"_i":"frame_0028.jpg","_t":2800,"_vc":89},{"_i":"frame_0036.jpg","_t":3600,"_vc":92},{"_i":"frame_0056.jpg","_t":5600,"_vc":100}]],"visualComplete":[5600],"lighthouse":[null],"pagespeed":[40]}}